{"output": [{"text": "1923160", "label": "TRANSACTIONTIME", "words": [{"id": 35, "box": [256.0, 353.0, 356.0, 373.0], "text": "1923160"}]}, {"text": "8290607", "label": "RECEIPTNUMBER", "words": [{"id": 37, "box": [78.0, 410.0, 177.0, 432.0], "text": "8290607"}]}, {"text": "enTedAple500ml", "label": "ITEMS", "words": [{"id": 60, "box": [68.0, 581.0, 234.0, 606.0], "text": "enTedAple500ml"}]}, {"text": "IChdogForkftee", "label": "ITEMS", "words": [{"id": 62, "box": [39.0, 610.0, 212.0, 635.0], "text": "IChdogForkftee"}]}, {"text": "50.000", "label": "PRICE", "words": [{"id": 64, "box": [327.0, 549.0, 404.0, 579.0], "text": "50.000"}]}, {"text": "128.10", "label": "TOTAL", "words": [{"id": 74, "box": [327.0, 669.0, 404.0, 696.0], "text": "128.10"}]}, {"text": "13.71", "label": "VATTAX", "words": [{"id": 88, "box": [339.0, 813.0, 398.0, 840.0], "text": "13.71"}]}, {"text": "0.00", "label": "VATTAX", "words": [{"id": 92, "box": [347.0, 872.0, 401.0, 899.0], "text": "0.00"}]}, {"label": "MERCHANTNAME", "text": "7", "words": [{"id": 0, "box": [128.0, 21.0, 355.0, 73.0], "text": "7"}]}, {"label": "MERCHANTNAME", "text": "-", "words": [{"id": 1, "box": [128.0, 21.0, 355.0, 73.0], "text": "-"}]}, {"label": "MERCHANTNAME", "text": "ELEVEN", "words": [{"id": 2, "box": [128.0, 21.0, 355.0, 73.0], "text": "ELEVEN"}]}, {"label": "MERCHANTADDRESS", "text": "roblacion", "words": [{"id": 23, "box": [69.0, 237.0, 193.0, 259.0], "text": "roblacion"}]}, {"label": "MERCHANTADDRESS", "text": ",", "words": [{"id": 24, "box": [69.0, 237.0, 193.0, 259.0], "text": ","}]}, {"label": "MERCHANTADDRESS", "text": "Leon", "words": [{"id": 25, "box": [195.0, 237.0, 266.0, 259.0], "text": "Leon"}]}, {"label": "MERCHANTADDRESS", "text": ",", "words": [{"id": 26, "box": [195.0, 237.0, 266.0, 259.0], "text": ","}]}, {"label": "MERCHANTADDRESS", "text": "Mould", "words": [{"id": 27, "box": [269.0, 237.0, 354.0, 259.0], "text": "Mould"}]}, {"label": "MERCHANTADDRESS", "text": ".", "words": [{"id": 28, "box": [269.0, 237.0, 354.0, 259.0], "text": "."}]}, {"label": "MERCHANTADDRESS", "text": "Philippines", "words": [{"id": 29, "box": [138.0, 264.0, 273.0, 286.0], "text": "Philippines"}]}, {"label": "TRANSACTIONDATE", "text": "04", "words": [{"id": 30, "box": [66.0, 353.0, 254.0, 373.0], "text": "04"}]}, {"label": "TRANSACTIONDATE", "text": "/", "words": [{"id": 31, "box": [66.0, 353.0, 254.0, 373.0], "text": "/"}]}, {"label": "TRANSACTIONDATE", "text": "8", "words": [{"id": 32, "box": [66.0, 353.0, 254.0, 373.0], "text": "8"}]}, {"label": "TRANSACTIONDATE", "text": "/", "words": [{"id": 33, "box": [66.0, 353.0, 254.0, 373.0], "text": "/"}]}, {"label": "TRANSACTIONDATE", "text": "2730100", "words": [{"id": 34, "box": [66.0, 353.0, 254.0, 373.0], "text": "2730100"}]}, {"label": "RECEIPTNUMBER", "text": "#", "words": [{"id": 43, "box": [79.0, 437.0, 142.0, 462.0], "text": "#"}]}, {"label": "RECEIPTNUMBER", "text": "3058", "words": [{"id": 44, "box": [79.0, 437.0, 142.0, 462.0], "text": "3058"}]}, {"label": "ITEMS", "text": "MuguSt", "words": [{"id": 56, "box": [17.0, 551.0, 91.0, 578.0], "text": "MuguSt"}]}, {"label": "ITEMS", "text": "rwbryCo370mt", "words": [{"id": 57, "box": [94.0, 551.0, 233.0, 578.0], "text": "rwbryCo370mt"}]}, {"label": "PRICE", "text": "00U", "words": [{"id": 66, "box": [363.0, 580.0, 404.0, 606.0], "text": "00U"}]}, {"label": "PRICE", "text": "39.00V", "words": [{"id": 67, "box": [324.0, 610.0, 400.0, 637.0], "text": "39.00V"}]}]}